jamexp/__init__.py
jamexp/cli/helper.py
jamexp/cli/jckill.py
jamexp/cli/jcp_template.py
jamexp/cli/jhyd_clean.py
jamexp/cli/jlink.py
jamexp/cli/jnb_clean.py
jamexp/cli/jpin.py
jamexp/cli/jwb_check_running.py
jamexp/cli/jwb_clean.py
jamexp/cli/ngc_shell.py
jamexp/cli/star_file.py
jamexp/hyd/__init__.py
jamexp/hyd/folder.py
jamexp/template_data/.gitignore
jamexp/template_data/.pre-commit-config.yaml
jamexp/utils/__init__.py
jamexp/utils/os_shell.py
jamexp/utils/timer.py
jamexp/wandb_clean/__init__.py
jamexp/wandb_clean/filters.py
jamexp/wandb_clean/utils.py
jamexp-0.1.8.dist-info/METADATA
jamexp-0.1.8.dist-info/WHEEL
jamexp-0.1.8.dist-info/entry_points.txt
jamexp-0.1.8.dist-info/RECORD
