Metadata-Version: 2.1
Name: jamexp
Version: 0.1.8
Summary: Jam Experiment helper
License: MIT
Keywords: jam,experiment
Author: Qinsheng
Author-email: qsh.zh27@gmail.com
Requires-Python: >=3.8,<3.11
Classifier: License :: OSI Approved :: MIT License
Classifier: Programming Language :: Python :: 3
Classifier: Programming Language :: Python :: 3.8
Classifier: Programming Language :: Python :: 3.9
Classifier: Programming Language :: Python :: 3.10
Requires-Dist: GitPython (>=3.1.17,<4.0.0)
Requires-Dist: Pillow (>=8.2.0,<9.0.0)
Requires-Dist: gpustat (>=0.6.0,<0.7.0)
Requires-Dist: hydra-core (>=1.0.6,<2.0.0)
Requires-Dist: loguru (>=0.5.3,<0.6.0)
Requires-Dist: numpy (>=1.20.3,<2.0.0)
Requires-Dist: pandas (>=1.5.3,<2.0.0)
Requires-Dist: pyfzf (>=0.2.2,<0.3.0)
Requires-Dist: pylint (>=2.8.3,<3.0.0)
Requires-Dist: scipy (>=1.6.3,<2.0.0)
Requires-Dist: typer (>=0.3.2,<0.4.0)
Requires-Dist: wandb (>=0.10.30,<0.11.0)
